timmopytemplate/__init__.py
timmopytemplate/__main__.py
timmopytemplate/_version.py
timmopytemplate-1.0.0.dist-info/METADATA
timmopytemplate-1.0.0.dist-info/WHEEL
timmopytemplate-1.0.0.dist-info/top_level.txt
timmopytemplate-1.0.0.dist-info/RECORD
